{"Id":"f75d65e6-b0a6-4954-af10-822b478c29e2","LogDateUtc":"2022-12-18T09:56:58.2122191Z","IpAddress":"::1","Culture":"en-US","Url":"/csscsr/js/blog-comments.js","ShortUrl":"/csscsr/js/blog-comments.js","Thread":".NET ThreadPool Worker","LogLevel":"Debug","Logger":"cloudscribe.Multitenancy.Internal.TenantResolutionMiddleware","Message":"TenantContext Resolved. Adding to HttpContext.","StateJson":"[{\"Key\":\"{OriginalFormat}\",\"Value\":\"TenantContext Resolved. Adding to HttpContext.\"}]","EventId":0}