{"Id":"037cf6bd-47bb-4314-838f-9c2aa3e2d27f","LogDateUtc":"2022-11-04T17:35:16.7622858Z","IpAddress":"::ffff:11.5.0.124","Culture":"en-US","Url":"/account/login","ShortUrl":"/account/login","Thread":".NET ThreadPool Worker","LogLevel":"Information","Logger":"Microsoft.AspNetCore.Mvc.StatusCodeResult","Message":"Executing StatusCodeResult, setting HTTP status code 400","StateJson":"[{\"Key\":\"StatusCode\",\"Value\":400},{\"Key\":\"{OriginalFormat}\",\"Value\":\"Executing StatusCodeResult, setting HTTP status code {StatusCode}\"}]","EventId":1}