{"Id":"fbe755c1-8c51-4bbc-bcd6-c2c0a0f1050d","LogDateUtc":"2022-12-18T09:56:10.6948043Z","IpAddress":"::1","Culture":"fi-FI","Url":"/blog","ShortUrl":"/blog","Thread":"","LogLevel":"Information","Logger":"Microsoft.AspNetCore.Mvc.ViewFeatures.ViewResultExecutor","Message":"Executed ViewResult - view Index executed in 939.3472ms.","StateJson":"[{\"Key\":\"ViewName\",\"Value\":\"Index\"},{\"Key\":\"ElapsedMilliseconds\",\"Value\":939.3472},{\"Key\":\"{OriginalFormat}\",\"Value\":\"Executed ViewResult - view {ViewName} executed in {ElapsedMilliseconds}ms.\"}]","EventId":4}