{"Id":"0b2d46b4-267d-4b36-b444-7d8e29993d28","LogDateUtc":"2022-12-18T14:08:43.3402839Z","IpAddress":"::1","Culture":"en-US","Url":"/custom1/js/bootstrap.bundle.js","ShortUrl":"/custom1/js/bootstrap.bundle.js","Thread":".NET ThreadPool Worker","LogLevel":"Debug","Logger":"cloudscribe.Multitenancy.Internal.TenantResolutionMiddleware","Message":"TenantContext Resolved. Adding to HttpContext.","StateJson":"[{\"Key\":\"{OriginalFormat}\",\"Value\":\"TenantContext Resolved. Adding to HttpContext.\"}]","EventId":0}