{"Id":"13c1fee4-b7a5-410f-81f2-58baf5fbc605","LogDateUtc":"2022-12-18T14:15:05.6332833Z","IpAddress":"::1","Culture":"en-US","Url":"/siteadmin/siteinfo","ShortUrl":"/siteadmin/siteinfo","Thread":".NET ThreadPool Worker","LogLevel":"Debug","Logger":"cloudscribe.Multitenancy.Internal.TenantResolutionMiddleware","Message":"Resolving TenantContext using SiteResolver.","StateJson":"[{\"Key\":\"loggerType\",\"Value\":\"SiteResolver\"},{\"Key\":\"{OriginalFormat}\",\"Value\":\"Resolving TenantContext using {loggerType}.\"}]","EventId":0}