{"Id":"6709b8ae-6b46-46d7-8753-0d64028df7fa","LogDateUtc":"2022-11-16T17:37:20.2008442Z","IpAddress":"::1","Culture":"fi-FI","Url":"/siteadmin/siteinfo","ShortUrl":"/siteadmin/siteinfo","Thread":".NET ThreadPool Worker","LogLevel":"Information","Logger":"Microsoft.AspNetCore.Mvc.ViewFeatures.ViewResultExecutor","Message":"Executed ViewResult - view SiteInfo executed in 138.3796ms.","StateJson":"[{\"Key\":\"ViewName\",\"Value\":\"SiteInfo\"},{\"Key\":\"ElapsedMilliseconds\",\"Value\":138.3796},{\"Key\":\"{OriginalFormat}\",\"Value\":\"Executed ViewResult - view {ViewName} executed in {ElapsedMilliseconds}ms.\"}]","EventId":4}