{"Id":"d987a415-e569-4565-8e1a-04c7e1ddf9e5","LogDateUtc":"2022-11-16T16:52:57.1167884Z","IpAddress":"::1","Culture":"fi-FI","Url":"/","ShortUrl":"/","Thread":".NET ThreadPool Worker","LogLevel":"Information","Logger":"Microsoft.AspNetCore.Authentication.Cookies.CookieAuthenticationHandler","Message":"Identity.Application was not authenticated. Failure message: Unprotect ticket failed","StateJson":"[{\"Key\":\"AuthenticationScheme\",\"Value\":\"Identity.Application\"},{\"Key\":\"FailureMessage\",\"Value\":\"Unprotect ticket failed\"},{\"Key\":\"{OriginalFormat}\",\"Value\":\"{AuthenticationScheme} was not authenticated. Failure message: {FailureMessage}\"}]","EventId":7}