{"Id":"c18c4096-ff13-4961-8b08-0d05157b860b","LogDateUtc":"2022-11-04T17:36:49.0994408Z","IpAddress":"::1","Culture":"en-US","Url":"/contact","ShortUrl":"/contact","Thread":"","LogLevel":"Information","Logger":"Microsoft.AspNetCore.Mvc.Infrastructure.ControllerActionInvoker","Message":"Executed action cloudscribe.SimpleContactForm.Controllers.ContactController.Index (cloudscribe.SimpleContactForm) in 300.7807ms","StateJson":"[{\"Key\":\"ActionName\",\"Value\":\"cloudscribe.SimpleContactForm.Controllers.ContactController.Index (cloudscribe.SimpleContactForm)\"},{\"Key\":\"ElapsedMilliseconds\",\"Value\":300.7807},{\"Key\":\"{OriginalFormat}\",\"Value\":\"Executed action {ActionName} in {ElapsedMilliseconds}ms\"}]","EventId":2}