{"Id":"39aeab9a-af93-4100-8aa1-aff0bbd745f2","LogDateUtc":"2022-11-28T13:34:40.3772845Z","IpAddress":"::1","Culture":"fi-FI","Url":"/siteadmin","ShortUrl":"/siteadmin","Thread":"","LogLevel":"Information","Logger":"Microsoft.AspNetCore.Mvc.ViewFeatures.ViewResultExecutor","Message":"Executed ViewResult - view Index executed in 68.2077ms.","StateJson":"[{\"Key\":\"ViewName\",\"Value\":\"Index\"},{\"Key\":\"ElapsedMilliseconds\",\"Value\":68.2077},{\"Key\":\"{OriginalFormat}\",\"Value\":\"Executed ViewResult - view {ViewName} executed in {ElapsedMilliseconds}ms.\"}]","EventId":4}