{"Id":"557f21ba-6d1c-4603-a788-e64dd6dd8aaf","LogDateUtc":"2022-11-28T13:31:59.2218569Z","IpAddress":"::1","Culture":"fi-FI","Url":"/filemanager/upload","ShortUrl":"/filemanager/upload","Thread":".NET ThreadPool Worker","LogLevel":"Information","Logger":"Microsoft.AspNetCore.Mvc.Infrastructure.SystemTextJsonResultExecutor","Message":"Executing JsonResult, writing value of type 'System.Collections.Generic.List`1[[cloudscribe.FileManager.Web.Models.UploadResult, cloudscribe.FileManager.Web, Version=6.0.2.0, Culture=neutral, PublicKeyToken=null]]'.","StateJson":"[{\"Key\":\"Type\",\"Value\":\"System.Collections.Generic.List`1[[cloudscribe.FileManager.Web.Models.UploadResult, cloudscribe.FileManager.Web, Version=6.0.2.0, Culture=neutral, PublicKeyToken=null]]\"},{\"Key\":\"{OriginalFormat}\",\"Value\":\"Executing JsonResult, writing value of type '{Type}'.\"}]","EventId":1}