{"Id":"8cc17d22-9d9b-404e-96d1-db6dc7c1e2b5","LogDateUtc":"2022-11-28T13:31:57.1478314Z","IpAddress":"::1","Culture":"fi-FI","Url":"/filemanager/upload","ShortUrl":"/filemanager/upload","Thread":".NET ThreadPool Worker","LogLevel":"Information","Logger":"Microsoft.AspNetCore.Mvc.Infrastructure.ControllerActionInvoker","Message":"Executed action cloudscribe.FileManager.Web.Controllers.FileManagerController.Upload (cloudscribe.FileManager.Web) in 3984.2248ms","StateJson":"[{\"Key\":\"ActionName\",\"Value\":\"cloudscribe.FileManager.Web.Controllers.FileManagerController.Upload (cloudscribe.FileManager.Web)\"},{\"Key\":\"ElapsedMilliseconds\",\"Value\":3984.2248},{\"Key\":\"{OriginalFormat}\",\"Value\":\"Executed action {ActionName} in {ElapsedMilliseconds}ms\"}]","EventId":2}