{"Id":"f5ff2932-7b22-4a02-9728-928a490d9bcd","LogDateUtc":"2022-11-28T13:16:56.2245166Z","IpAddress":"::1","Culture":"fi-FI","Url":"/filemanager/createfolder","ShortUrl":"/filemanager/createfolder","Thread":".NET ThreadPool Worker","LogLevel":"Information","Logger":"Microsoft.AspNetCore.Mvc.Infrastructure.SystemTextJsonResultExecutor","Message":"Executing JsonResult, writing value of type 'cloudscribe.FileManager.Web.Models.OperationResult'.","StateJson":"[{\"Key\":\"Type\",\"Value\":\"cloudscribe.FileManager.Web.Models.OperationResult\"},{\"Key\":\"{OriginalFormat}\",\"Value\":\"Executing JsonResult, writing value of type '{Type}'.\"}]","EventId":1}