{"Id":"70cd8d21-55e4-44a2-9a18-7da8937fb960","LogDateUtc":"2022-12-18T14:11:53.7461492Z","IpAddress":"::1","Culture":"fi-FI","Url":"/csscsr/css/simple-gallery.min.css","ShortUrl":"/csscsr/css/simple-gallery.min.css","Thread":".NET ThreadPool Worker","LogLevel":"Debug","Logger":"cloudscribe.SimpleContent.Web.Mvc.Controllers.CsscsrController","Message":"resource found for cloudscribe.SimpleContent.Web.css.simple-gallery.min.css","StateJson":"[{\"Key\":\"{OriginalFormat}\",\"Value\":\"resource found for cloudscribe.SimpleContent.Web.css.simple-gallery.min.css\"}]","EventId":0}