{"Id":"fa7c4855-109c-45e4-93e0-e31621469f34","LogDateUtc":"2022-11-04T19:30:49.1396588Z","IpAddress":"::1","Culture":"fr-FR","Url":"/csscsr/css/simple-gallery.min.css","ShortUrl":"/csscsr/css/simple-gallery.min.css","Thread":".NET ThreadPool Worker","LogLevel":"Information","Logger":"Microsoft.AspNetCore.Mvc.StatusCodeResult","Message":"Executing StatusCodeResult, setting HTTP status code 304","StateJson":"[{\"Key\":\"StatusCode\",\"Value\":304},{\"Key\":\"{OriginalFormat}\",\"Value\":\"Executing StatusCodeResult, setting HTTP status code {StatusCode}\"}]","EventId":1}