{"Id":"6d490161-6a52-4ac0-8108-ce41940cbaa9","LogDateUtc":"2022-12-18T14:13:15.5596833Z","IpAddress":"::1","Culture":"fi-FI","Url":"/blog/2022/11/04/test","ShortUrl":"/blog/2022/11/04/test","Thread":"","LogLevel":"Information","Logger":"Microsoft.AspNetCore.Mvc.Infrastructure.ControllerActionInvoker","Message":"Executed action cloudscribe.SimpleContent.Web.Mvc.Controllers.BlogController.Post (cloudscribe.SimpleContent.Web) in 243.6996ms","StateJson":"[{\"Key\":\"ActionName\",\"Value\":\"cloudscribe.SimpleContent.Web.Mvc.Controllers.BlogController.Post (cloudscribe.SimpleContent.Web)\"},{\"Key\":\"ElapsedMilliseconds\",\"Value\":243.6996},{\"Key\":\"{OriginalFormat}\",\"Value\":\"Executed action {ActionName} in {ElapsedMilliseconds}ms\"}]","EventId":2}