{"Id":"78b831cd-a5c9-4f03-b48b-d1290d8974e2","LogDateUtc":"2022-12-18T12:15:23.0551398Z","IpAddress":"::1","Culture":"fi-FI","Url":"/","ShortUrl":"/","Thread":".NET ThreadPool Worker","LogLevel":"Information","Logger":"Microsoft.AspNetCore.Mvc.Infrastructure.ControllerActionInvoker","Message":"Executed action cloudscribe.SimpleContent.Web.Mvc.Controllers.PageController.Index (cloudscribe.SimpleContent.Web) in 4227.1249ms","StateJson":"[{\"Key\":\"ActionName\",\"Value\":\"cloudscribe.SimpleContent.Web.Mvc.Controllers.PageController.Index (cloudscribe.SimpleContent.Web)\"},{\"Key\":\"ElapsedMilliseconds\",\"Value\":4227.1249},{\"Key\":\"{OriginalFormat}\",\"Value\":\"Executed action {ActionName} in {ElapsedMilliseconds}ms\"}]","EventId":2}