{"Id":"28496cf9-00c3-43c5-86ec-0dcf5ece7eee","LogDateUtc":"2022-11-04T19:29:32.0286362Z","IpAddress":"::1","Culture":"en-US","Url":"/siteadmin","ShortUrl":"/siteadmin","Thread":".NET ThreadPool Worker","LogLevel":"Debug","Logger":"cloudscribe.Multitenancy.Internal.TenantResolutionMiddleware","Message":"Resolving TenantContext using SiteResolver.","StateJson":"[{\"Key\":\"loggerType\",\"Value\":\"SiteResolver\"},{\"Key\":\"{OriginalFormat}\",\"Value\":\"Resolving TenantContext using {loggerType}.\"}]","EventId":0}