{"Id":"51bbbb99-5c9f-4877-903d-cfeec75ddabc","LogDateUtc":"2022-11-04T19:33:14.4957428Z","IpAddress":"::1","Culture":"en-US","Url":"/api/rss","ShortUrl":"/api/rss","Thread":".NET ThreadPool Worker","LogLevel":"Debug","Logger":"cloudscribe.Multitenancy.Internal.TenantResolutionMiddleware","Message":"Resolving TenantContext using SiteResolver.","StateJson":"[{\"Key\":\"loggerType\",\"Value\":\"SiteResolver\"},{\"Key\":\"{OriginalFormat}\",\"Value\":\"Resolving TenantContext using {loggerType}.\"}]","EventId":0}