{"Id":"63d5f272-0f7d-4526-b3b4-8fc4e69e47af","LogDateUtc":"2022-11-28T13:56:10.5465619Z","IpAddress":"::1","Culture":"en-US","Url":"/filemanager/getfiletreejson","ShortUrl":"/filemanager/getfiletreejson","Thread":".NET ThreadPool Worker","LogLevel":"Debug","Logger":"cloudscribe.Multitenancy.Internal.TenantResolutionMiddleware","Message":"TenantContext Resolved. Adding to HttpContext.","StateJson":"[{\"Key\":\"{OriginalFormat}\",\"Value\":\"TenantContext Resolved. Adding to HttpContext.\"}]","EventId":0}